docs/__init__.py
fi/__init__.py
fi/bounded_executor.py
fi/client.py
fi/examples/__init__.py
fi/examples/rag_file.py
fi/utils/__init__.py
fi/utils/constants.py
fi/utils/errors.py
fi/utils/logging.py
fi/utils/types.py
fi/utils/utils.py
futureagi-1.1.0.dist-info/LICENSE.md
futureagi-1.1.0.dist-info/METADATA
futureagi-1.1.0.dist-info/WHEEL
futureagi-1.1.0.dist-info/top_level.txt
futureagi-1.1.0.dist-info/RECORD
