Metadata-Version: 2.1
Name: futureagi
Version: 1.1.0
Summary: Empowering GenAI teams to maintain peak model accuracy in production environments.
Home-page: https://github.com/future-agi/client
Author: Future AGI
Author-email: noreply@mail.futureagi.com
Classifier: Programming Language :: Python :: 3
Classifier: License :: OSI Approved :: MIT License
Classifier: Operating System :: OS Independent
Requires-Python: >=3.6
License-File: LICENSE.md
Requires-Dist: certifi ==2024.6.2
Requires-Dist: charset-normalizer ==3.3.2
Requires-Dist: idna ==3.7
Requires-Dist: numpy ==1.26.4
Requires-Dist: pandas ==2.2.2
Requires-Dist: python-dateutil ==2.9.0.post0
Requires-Dist: pytz ==2024.1
Requires-Dist: requests ==2.32.3
Requires-Dist: requests-futures ==1.0.1
Requires-Dist: six ==1.16.0
Requires-Dist: tzdata ==2024.1
Requires-Dist: urllib3 ==2.2.2
